scatl/__init__.py
scatl/apps.py
scatl/plugins.py
scatl/urls.py
scatl/api/__init__.py
scatl/api/api_populator.py
scatl/api/pagination.py
scatl/api/serializers/__init__.py
scatl/api/serializers/product.py
scatl/api/serializers/query_data.py
scatl/api/views/__init__.py
scatl/api/views/product.py
scatl/api/views/query_data.py
scatl/migrations/0001_initial.py
scatl/migrations/0002_change_default_page_size.py
scatl/migrations/__init__.py
scatl/models/__init__.py
scatl/models/config.py
scatl/services/__init__.py
scatl/services/filters.py
scatl/services/product/__init__.py
scatl/services/product/price.py
scatl/services/query_data/__init__.py
scatl/services/query_data/complementer.py
scatl/services/query_data/query_data.py
scatl/static/scatl/dist/app.js
scatl/static/scatl/dist/polyfills.js
scatl/static/scatl/dist/vendor.css
scatl/static/scatl/dist/vendor.js
scatl/templates/scatl/catalog.jinja
scatl/templates/scatl/index.jinja
scatl/tests/__init__.py
scatl/tests/test_index_render.py
scatl/tests/test_integration.py
scatl/tests/api/__init__.py
scatl/tests/api/test_pagination.py
scatl/tests/api/views/__init__.py
scatl/tests/api/views/test_products.py
scatl/tests/api/views/test_query_data.py
scatl/tests/api/views/test_query_data_deserialization.py
scatl/tests/services/__init__.py
scatl/tests/services/test_product_price.py
scatl/tests/services/filters/__init__.py
scatl/tests/services/filters/test_attrim.py
scatl/tests/services/filters/test_filters.py
scatl/tests/services/filters/test_shuup_attrs.py
scatl/tests/services/filters/test_sorting.py
scatl/tests/services/query_data/__init__.py
scatl/tests/services/query_data/test_complementer.py
scatl/tests/testproject/__init__.py
scatl/tests/testproject/manage.py
scatl/tests/testproject/settings.py
scatl/tests/testutils/__init__.py
scatl/tests/testutils/filters_test_case.py
shuup_scatl-0.2.2.3.dist-info/DESCRIPTION.rst
shuup_scatl-0.2.2.3.dist-info/METADATA
shuup_scatl-0.2.2.3.dist-info/RECORD
shuup_scatl-0.2.2.3.dist-info/WHEEL
shuup_scatl-0.2.2.3.dist-info/entry_points.txt
shuup_scatl-0.2.2.3.dist-info/metadata.json
shuup_scatl-0.2.2.3.dist-info/top_level.txt
