Metadata-Version: 2.0
Name: shuup-scatl
Version: 0.2.2.3
Summary: Catalog addon for Shuup E-Commerce Platform
Home-page: https://gitlab.com/nilit/shuup-scatl
Author: UNKNOWN
Author-email: UNKNOWN
License: UNKNOWN
Keywords: shuup,attributes
Platform: UNKNOWN
Classifier: Development Status :: 4 - Beta
Classifier: Framework :: Django :: 1.9
Classifier: Intended Audience :: Developers
Classifier: Intended Audience :: Financial and Insurance Industry
Classifier: Topic :: Software Development
Classifier: Programming Language :: Python :: 3 :: Only
Classifier: Programming Language :: Python :: 3.5
Classifier: Topic :: Software Development :: Libraries :: Python Modules
Classifier: Topic :: Internet :: WWW/HTTP
Classifier: Topic :: Office/Business
Requires-Dist: django-solo (==1.1.2)
Requires-Dist: parameterized (<0.7,>=0.6.1)
Requires-Dist: psycopg2 (>=2.6.2,<3)
Requires-Dist: shuup (==2.0)
Requires-Dist: shuup-attrim (>=0.13.1.5,<0.14)
Requires-Dist: shuup-testutils (<0.13,>=0.12)
Requires-Dist: shuup-utils (>=0.7,<0.8)
